pg-extras/__init__.py
pg_extras/__init__.py
pg_extras-0.1.4.dist-info/LICENSE
pg_extras-0.1.4.dist-info/METADATA
pg_extras-0.1.4.dist-info/WHEEL
pg_extras-0.1.4.dist-info/top_level.txt
pg_extras-0.1.4.dist-info/RECORD
