Metadata-Version: 2.1
Name: pg-extras
Version: 0.1.4
Summary: Python PostgreSQL database performance insights. Locks, index usage, buffer cache hit ratios, vacuum stats and more.
Home-page: https://github.com/pawurb/python-pg-extras
Author: Pawel Urbanek
Author-email: contact@pawelurbanek.com
License: UNKNOWN
Platform: UNKNOWN
Classifier: Programming Language :: Python :: 3
Classifier: License :: OSI Approved :: MIT License
Classifier: Operating System :: OS Independent
Classifier: Topic :: Software Development :: Libraries :: Python Modules
Classifier: Topic :: Database
Requires-Python: >=3.6
Requires-Dist: SQLAlchemy (>=1.3)
Requires-Dist: setuptools
Requires-Dist: tabulate
Requires-Dist: psycopg2
